pymssql.so
_mssql.so
pymssql_linux-2.1.6.dist-info/RECORD
pymssql_linux-2.1.6.dist-info/LICENSE
pymssql_linux-2.1.6.dist-info/METADATA
pymssql_linux-2.1.6.dist-info/WHEEL
pymssql_linux-2.1.6.dist-info/top_level.txt
pymssql_linux.libs/libsybdb-aa5d1ff6.so.5.1.0
