Metadata-Version: 1.2
Name: pymssql-linux
Version: 2.1.6
Summary: DB-API interface to Microsoft SQL Server for Python. (new Cython-based version)
Home-page: https://github.com/noisycomputation/pymssql-linux
Author: Damien Churchill
Author-email: damoxc@gmail.com
Maintainer: Noisy Computation
Maintainer-email: noisycomputation@gmail.com
License: LGPL
Keywords: mssql,SQL Server,database,DB-API
Platform: UNKNOWN
Classifier: Development Status :: 5 - Production/Stable
Classifier: Intended Audience :: Developers
Classifier: License :: OSI Approved :: GNU Library or Lesser General Public License (LGPL)
Classifier: Programming Language :: Python
Classifier: Programming Language :: Python :: 3
Classifier: Programming Language :: Python :: 3.7
Classifier: Programming Language :: Python :: 3.8
Classifier: Programming Language :: Python :: Implementation :: CPython
Classifier: Topic :: Database
Classifier: Topic :: Database :: Database Engines/Servers
Classifier: Topic :: Software Development :: Libraries :: Python Modules
Classifier: Operating System :: Microsoft :: Windows
Classifier: Operating System :: POSIX
Classifier: Operating System :: Unix
